README.md
setup.py
pyseistr_win.egg-info/PKG-INFO
pyseistr_win.egg-info/SOURCES.txt
pyseistr_win.egg-info/dependency_links.txt
pyseistr_win.egg-info/not-zip-safe
pyseistr_win.egg-info/requires.txt
pyseistr_win.egg-info/top_level.txt
pyseistrw/__init__.py
pyseistrw/bp.py
pyseistrw/das.py
pyseistrw/dip2d.py
pyseistrw/dip3d.py
pyseistrw/divne.py
pyseistrw/fk.py
pyseistrw/mf.py
pyseistrw/operators.py
pyseistrw/plot.py
pyseistrw/pwsmooth.py
pyseistrw/pwspray2d.py
pyseistrw/pwspray3d.py
pyseistrw/ricker.py
pyseistrw/sint.py
pyseistrw/smooth.py
pyseistrw/soint2d.py
pyseistrw/soint3d.py
pyseistrw/solvers.py
pyseistrw/somean2d.py
pyseistrw/somean3d.py
pyseistrw/somf2d.py
pyseistrw/somf3d.py
pyseistrw/synthetics.py