Metadata-Version: 2.1
Name: pyseistr-win
Version: 0.0.1.1
Summary: A python package for structural denoising and interpolation of multi-channel seismic data
Home-page: https://github.com/aaspip/pyseistr-win
Author: pyseistr-win developing team
Author-email: chenyk2016@gmail.com
License: GNU General Public License, Version 3 (GPLv3)
Keywords: seismology,earthquake seismology,exploration seismology,array seismology,denoising,science,engineering,structure,local slope,filtering
Classifier: Development Status :: 4 - Beta
Classifier: Intended Audience :: Developers
Classifier: Intended Audience :: Science/Research
Classifier: Operating System :: Unix
Classifier: Operating System :: POSIX
Classifier: Operating System :: Microsoft :: Windows
Classifier: Programming Language :: Python
Classifier: Programming Language :: Python :: 3.8
Classifier: Programming Language :: Python :: Implementation :: CPython
Classifier: Topic :: Scientific/Engineering
Classifier: Topic :: Scientific/Engineering :: Physics
Classifier: License :: OSI Approved :: GNU General Public License v3 (GPLv3)
Provides-Extra: docs
